Workbook

Sheet Parámetros
A1: PARÁMETROS – FLUJO DE CAJA AIRBNB
A3: HORIZONTE Y OPERACIÓN
A4: Horizonte (meses) | B4: 36
A5: Meses de gracia (sin ingresos) | B5: 6
A6: ADR promedio (CLP / noche) | B6: 38000
A7: Noches promedio por mes | B7: 21
A8: Crecimiento anual ADR (%) | B8: 0.03
A10: COSTOS OPERATIVOS (CLP/mes)
A11: Comisión administración/Airbnb | B11: 0.18
A12: Gastos comunes | B12: 90000
A13: Servicios (luz, agua, internet) | B13: 60000
A14: Fondo de mantención | B14: 40000
A15: Dividendo / arriendo | B15: 274000
A17: INVERSIÓN Y FINANCIAMIENTO
A18: Inversión inicial (amoblado) | B18: 3200000
A19: Tasa de descuento anual (%) | B19: 0.12
A22: Las celdas en amarillo son editables. Todos los demás valores se calculan automáticamente.

Sheet Flujo de Caja Mensual
A1: FLUJO DE CAJA MENSUAL – AIRBNB
A2: Mes | B2: Período | C2: ADR (CLP/noche) | D2: Noches promedio | E2: Ing. Brutos (CLP) | F2: Comisión Admin/Airbnb | G2: Ing. Netos (CLP) | H2: Gastos Comunes | I2: Servicios | J2: Fondo Mantención | K2: Dividendo | L2: Total Egresos | M2: Flujo Neto (CLP) | N2: Flujo Acumulado (CLP)
A3: 1 | B3: Jan 2025 | C3: 0 | D3: =IF(1<='Parámetros'!$B$5,0,'Parámetros'!$B$7) | E3: =C3*D3 | F3: =E3*'Parámetros'!$B$11 | G3: =E3-F3 | H3: ='Parámetros'!$B$12 | I3: ='Parámetros'!$B$13 | J3: ='Parámetros'!$B$14 | K3: ='Parámetros'!$B$15 | L3: =SUM(H3:K3) | M3: =G3-L3 | N3: =-'Parámetros'!$B$18+M3
A4: 2 | B4: Feb 2025 | C4: 0 | D4: =IF(2<='Parámetros'!$B$5,0,'Parámetros'!$B$7) | E4: =C4*D4 | F4: =E4*'Parámetros'!$B$11 | G4: =E4-F4 | H4: ='Parámetros'!$B$12 | I4: ='Parámetros'!$B$13 | J4: ='Parámetros'!$B$14 | K4: ='Parámetros'!$B$15 | L4: =SUM(H4:K4) | M4: =G4-L4 | N4: =N3+M4
A5: 3 | B5: Mar 2025 | C5: 0 | D5: =IF(3<='Parámetros'!$B$5,0,'Parámetros'!$B$7) | E5: =C5*D5 | F5: =E5*'Parámetros'!$B$11 | G5: =E5-F5 | H5: ='Parámetros'!$B$12 | I5: ='Parámetros'!$B$13 | J5: ='Parámetros'!$B$14 | K5: ='Parámetros'!$B$15 | L5: =SUM(H5:K5) | M5: =G5-L5 | N5: =N4+M5
A6: 4 | B6: Apr 2025 | C6: 0 | D6: =IF(4<='Parámetros'!$B$5,0,'Parámetros'!$B$7) | E6: =C6*D6 | F6: =E6*'Parámetros'!$B$11 | G6: =E6-F6 | H6: ='Parámetros'!$B$12 | I6: ='Parámetros'!$B$13 | J6: ='Parámetros'!$B$14 | K6: ='Parámetros'!$B$15 | L6: =SUM(H6:K6) | M6: =G6-L6 | N6: =N5+M6
A7: 5 | B7: May 2025 | C7: 0 | D7: =IF(5<='Parámetros'!$B$5,0,'Parámetros'!$B$7) | E7: =C7*D7 | F7: =E7*'Parámetros'!$B$11 | G7: =E7-F7 | H7: ='Parámetros'!$B$12 | I7: ='Parámetros'!$B$13 | J7: ='Parámetros'!$B$14 | K7: ='Parámetros'!$B$15 | L7: =SUM(H7:K7) | M7: =G7-L7 | N7: =N6+M7
A8: 6 | B8: Jun 2025 | C8: 0 | D8: =IF(6<='Parámetros'!$B$5,0,'Parámetros'!$B$7) | E8: =C8*D8 | F8: =E8*'Parámetros'!$B$11 | G8: =E8-F8 | H8: ='Parámetros'!$B$12 | I8: ='Parámetros'!$B$13 | J8: ='Parámetros'!$B$14 | K8: ='Parámetros'!$B$15 | L8: =SUM(H8:K8) | M8: =G8-L8 | N8: =N7+M8
A9: 7 | B9: Jul 2025 | C9: ='Parámetros'!$B$6*(1+'Parámetros'!$B$8)^0 | D9: =IF(7<='Parámetros'!$B$5,0,'Parámetros'!$B$7) | E9: =C9*D9 | F9: =E9*'Parámetros'!$B$11 | G9: =E9-F9 | H9: ='Parámetros'!$B$12 | I9: ='Parámetros'!$B$13 | J9: ='Parámetros'!$B$14 | K9: ='Parámetros'!$B$15 | L9: =SUM(H9:K9) | M9: =G9-L9 | N9: =N8+M9
A10: 8 | B10: Aug 2025 | C10: ='Parámetros'!$B$6*(1+'Parámetros'!$B$8)^0 | D10: =IF(8<='Parámetros'!$B$5,0,'Parámetros'!$B$7) | E10: =C10*D10 | F10: =E10*'Parámetros'!$B$11 | G10: =E10-F10 | H10: ='Parámetros'!$B$12 | I10: ='Parámetros'!$B$13 | J10: ='Parámetros'!$B$14 | K10: ='Parámetros'!$B$15 | L10: =SUM(H10:K10) | M10: =G10-L10 | N10: =N9+M10
A11: 9 | B11: Sep 2025 | C11: ='Parámetros'!$B$6*(1+'Parámetros'!$B$8)^0 | D11: =IF(9<='Parámetros'!$B$5,0,'Parámetros'!$B$7) | E11: =C11*D11 | F11: =E11*'Parámetros'!$B$11 | G11: =E11-F11 | H11: ='Parámetros'!$B$12 | I11: ='Parámetros'!$B$13 | J11: ='Parámetros'!$B$14 | K11: ='Parámetros'!$B$15 | L11: =SUM(H11:K11) | M11: =G11-L11 | N11: =N10+M11
A12: 10 | B12: Oct 2025 | C12: ='Parámetros'!$B$6*(1+'Parámetros'!$B$8)^0 | D12: =IF(10<='Parámetros'!$B$5,0,'Parámetros'!$B$7) | E12: =C12*D12 | F12: =E12*'Parámetros'!$B$11 | G12: =E12-F12 | H12: ='Parámetros'!$B$12 | I12: ='Parámetros'!$B$13 | J12: ='Parámetros'!$B$14 | K12: ='Parámetros'!$B$15 | L12: =SUM(H12:K12) | M12: =G12-L12 | N12: =N11+M12
A13: 11 | B13: Nov 2025 | C13: ='Parámetros'!$B$6*(1+'Parámetros'!$B$8)^0 | D13: =IF(11<='Parámetros'!$B$5,0,'Parámetros'!$B$7) | E13: =C13*D13 | F13: =E13*'Parámetros'!$B$11 | G13: =E13-F13 | H13: ='Parámetros'!$B$12 | I13: ='Parámetros'!$B$13 | J13: ='Parámetros'!$B$14 | K13: ='Parámetros'!$B$15 | L13: =SUM(H13:K13) | M13: =G13-L13 | N13: =N12+M13
A14: 12 | B14: Dec 2025 | C14: ='Parámetros'!$B$6*(1+'Parámetros'!$B$8)^0 | D14: =IF(12<='Parámetros'!$B$5,0,'Parámetros'!$B$7) | E14: =C14*D14 | F14: =E14*'Parámetros'!$B$11 | G14: =E14-F14 | H14: ='Parámetros'!$B$12 | I14: ='Parámetros'!$B$13 | J14: ='Parámetros'!$B$14 | K14: ='Parámetros'!$B$15 | L14: =SUM(H14:K14) | M14: =G14-L14 | N14: =N13+M14
A15: 13 | B15: Jan 2026 | C15: ='Parámetros'!$B$6*(1+'Parámetros'!$B$8)^1 | D15: =IF(13<='Parámetros'!$B$5,0,'Parámetros'!$B$7) | E15: =C15*D15 | F15: =E15*'Parámetros'!$B$11 | G15: =E15-F15 | H15: ='Parámetros'!$B$12 | I15: ='Parámetros'!$B$13 | J15: ='Parámetros'!$B$14 | K15: ='Parámetros'!$B$15 | L15: =SUM(H15:K15) | M15: =G15-L15 | N15: =N14+M15
A16: 14 | B16: Feb 2026 | C16: ='Parámetros'!$B$6*(1+'Parámetros'!$B$8)^1 | D16: =IF(14<='Parámetros'!$B$5,0,'Parámetros'!$B$7) | E16: =C16*D16 | F16: =E16*'Parámetros'!$B$11 | G16: =E16-F16 | H16: ='Parámetros'!$B$12 | I16: ='Parámetros'!$B$13 | J16: ='Parámetros'!$B$14 | K16: ='Parámetros'!$B$15 | L16: =SUM(H16:K16) | M16: =G16-L16 | N16: =N15+M16
A17: 15 | B17: Mar 2026 | C17: ='Parámetros'!$B$6*(1+'Parámetros'!$B$8)^1 | D17: =IF(15<='Parámetros'!$B$5,0,'Parámetros'!$B$7) | E17: =C17*D17 | F17: =E17*'Parámetros'!$B$11 | G17: =E17-F17 | H17: ='Parámetros'!$B$12 | I17: ='Parámetros'!$B$13 | J17: ='Parámetros'!$B$14 | K17: ='Parámetros'!$B$15 | L17: =SUM(H17:K17) | M17: =G17-L17 | N17: =N16+M17
A18: 16 | B18: Apr 2026 | C18: ='Parámetros'!$B$6*(1+'Parámetros'!$B$8)^1 | D18: =IF(16<='Parámetros'!$B$5,0,'Parámetros'!$B$7) | E18: =C18*D18 | F18: =E18*'Parámetros'!$B$11 | G18: =E18-F18 | H18: ='Parámetros'!$B$12 | I18: ='Parámetros'!$B$13 | J18: ='Parámetros'!$B$14 | K18: ='Parámetros'!$B$15 | L18: =SUM(H18:K18) | M18: =G18-L18 | N18: =N17+M18
A19: 17 | B19: May 2026 | C19: ='Parámetros'!$B$6*(1+'Parámetros'!$B$8)^1 | D19: =IF(17<='Parámetros'!$B$5,0,'Parámetros'!$B$7) | E19: =C19*D19 | F19: =E19*'Parámetros'!$B$11 | G19: =E19-F19 | H19: ='Parámetros'!$B$12 | I19: ='Parámetros'!$B$13 | J19: ='Parámetros'!$B$14 | K19: ='Parámetros'!$B$15 | L19: =SUM(H19:K19) | M19: =G19-L19 | N19: =N18+M19
A20: 18 | B20: Jun 2026 | C20: ='Parámetros'!$B$6*(1+'Parámetros'!$B$8)^1 | D20: =IF(18<='Parámetros'!$B$5,0,'Parámetros'!$B$7) | E20: =C20*D20 | F20: =E20*'Parámetros'!$B$11 | G20: =E20-F20 | H20: ='Parámetros'!$B$12 | I20: ='Parámetros'!$B$13 | J20: ='Parámetros'!$B$14 | K20: ='Parámetros'!$B$15 | L20: =SUM(H20:K20) | M20: =G20-L20 | N20: =N19+M20
A21: 19 | B21: Jul 2026 | C21: ='Parámetros'!$B$6*(1+'Parámetros'!$B$8)^1 | D21: =IF(19<='Parámetros'!$B$5,0,'Parámetros'!$B$7) | E21: =C21*D21 | F21: =E21*'Parámetros'!$B$11 | G21: =E21-F21 | H21: ='Parámetros'!$B$12 | I21: ='Parámetros'!$B$13 | J21: ='Parámetros'!$B$14 | K21: ='Parámetros'!$B$15 | L21: =SUM(H21:K21) | M21: =G21-L21 | N21: =N20+M21
A22: 20 | B22: Aug 2026 | C22: ='Parámetros'!$B$6*(1+'Parámetros'!$B$8)^1 | D22: =IF(20<='Parámetros'!$B$5,0,'Parámetros'!$B$7) | E22: =C22*D22 | F22: =E22*'Parámetros'!$B$11 | G22: =E22-F22 | H22: ='Parámetros'!$B$12 | I22: ='Parámetros'!$B$13 | J22: ='Parámetros'!$B$14 | K22: ='Parámetros'!$B$15 | L22: =SUM(H22:K22) | M22: =G22-L22 | N22: =N21+M22
A23: 21 | B23: Sep 2026 | C23: ='Parámetros'!$B$6*(1+'Parámetros'!$B$8)^1 | D23: =IF(21<='Parámetros'!$B$5,0,'Parámetros'!$B$7) | E23: =C23*D23 | F23: =E23*'Parámetros'!$B$11 | G23: =E23-F23 | H23: ='Parámetros'!$B$12 | I23: ='Parámetros'!$B$13 | J23: ='Parámetros'!$B$14 | K23: ='Parámetros'!$B$15 | L23: =SUM(H23:K23) | M23: =G23-L23 | N23: =N22+M23
A24: 22 | B24: Oct 2026 | C24: ='Parámetros'!$B$6*(1+'Parámetros'!$B$8)^1 | D24: =IF(22<='Parámetros'!$B$5,0,'Parámetros'!$B$7) | E24: =C24*D24 | F24: =E24*'Parámetros'!$B$11 | G24: =E24-F24 | H24: ='Parámetros'!$B$12 | I24: ='Parámetros'!$B$13 | J24: ='Parámetros'!$B$14 | K24: ='Parámetros'!$B$15 | L24: =SUM(H24:K24) | M24: =G24-L24 | N24: =N23+M24
A25: 23 | B25: Nov 2026 | C25: ='Parámetros'!$B$6*(1+'Parámetros'!$B$8)^1 | D25: =IF(23<='Parámetros'!$B$5,0,'Parámetros'!$B$7) | E25: =C25*D25 | F25: =E25*'Parámetros'!$B$11 | G25: =E25-F25 | H25: ='Parámetros'!$B$12 | I25: ='Parámetros'!$B$13 | J25: ='Parámetros'!$B$14 | K25: ='Parámetros'!$B$15 | L25: =SUM(H25:K25) | M25: =G25-L25 | N25: =N24+M25
A26: 24 | B26: Dec 2026 | C26: ='Parámetros'!$B$6*(1+'Parámetros'!$B$8)^1 | D26: =IF(24<='Parámetros'!$B$5,0,'Parámetros'!$B$7) | E26: =C26*D26 | F26: =E26*'Parámetros'!$B$11 | G26: =E26-F26 | H26: ='Parámetros'!$B$12 | I26: ='Parámetros'!$B$13 | J26: ='Parámetros'!$B$14 | K26: ='Parámetros'!$B$15 | L26: =SUM(H26:K26) | M26: =G26-L26 | N26: =N25+M26
A27: 25 | B27: Jan 2027 | C27: ='Parámetros'!$B$6*(1+'Parámetros'!$B$8)^2 | D27: =IF(25<='Parámetros'!$B$5,0,'Parámetros'!$B$7) | E27: =C27*D27 | F27: =E27*'Parámetros'!$B$11 | G27: =E27-F27 | H27: ='Parámetros'!$B$12 | I27: ='Parámetros'!$B$13 | J27: ='Parámetros'!$B$14 | K27: ='Parámetros'!$B$15 | L27: =SUM(H27:K27) | M27: =G27-L27 | N27: =N26+M27
A28: 26 | B28: Feb 2027 | C28: ='Parámetros'!$B$6*(1+'Parámetros'!$B$8)^2 | D28: =IF(26<='Parámetros'!$B$5,0,'Parámetros'!$B$7) | E28: =C28*D28 | F28: =E28*'Parámetros'!$B$11 | G28: =E28-F28 | H28: ='Parámetros'!$B$12 | I28: ='Parámetros'!$B$13 | J28: ='Parámetros'!$B$14 | K28: ='Parámetros'!$B$15 | L28: =SUM(H28:K28) | M28: =G28-L28 | N28: =N27+M28
A29: 27 | B29: Mar 2027 | C29: ='Parámetros'!$B$6*(1+'Parámetros'!$B$8)^2 | D29: =IF(27<='Parámetros'!$B$5,0,'Parámetros'!$B$7) | E29: =C29*D29 | F29: =E29*'Parámetros'!$B$11 | G29: =E29-F29 | H29: ='Parámetros'!$B$12 | I29: ='Parámetros'!$B$13 | J29: ='Parámetros'!$B$14 | K29: ='Parámetros'!$B$15 | L29: =SUM(H29:K29) | M29: =G29-L29 | N29: =N28+M29
A30: 28 | B30: Apr 2027 | C30: ='Parámetros'!$B$6*(1+'Parámetros'!$B$8)^2 | D30: =IF(28<='Parámetros'!$B$5,0,'Parámetros'!$B$7) | E30: =C30*D30 | F30: =E30*'Parámetros'!$B$11 | G30: =E30-F30 | H30: ='Parámetros'!$B$12 | I30: ='Parámetros'!$B$13 | J30: ='Parámetros'!$B$14 | K30: ='Parámetros'!$B$15 | L30: =SUM(H30:K30) | M30: =G30-L30 | N30: =N29+M30
A31: 29 | B31: May 2027 | C31: ='Parámetros'!$B$6*(1+'Parámetros'!$B$8)^2 | D31: =IF(29<='Parámetros'!$B$5,0,'Parámetros'!$B$7) | E31: =C31*D31 | F31: =E31*'Parámetros'!$B$11 | G31: =E31-F31 | H31: ='Parámetros'!$B$12 | I31: ='Parámetros'!$B$13 | J31: ='Parámetros'!$B$14 | K31: ='Parámetros'!$B$15 | L31: =SUM(H31:K31) | M31: =G31-L31 | N31: =N30+M31
A32: 30 | B32: Jun 2027 | C32: ='Parámetros'!$B$6*(1+'Parámetros'!$B$8)^2 | D32: =IF(30<='Parámetros'!$B$5,0,'Parámetros'!$B$7) | E32: =C32*D32 | F32: =E32*'Parámetros'!$B$11 | G32: =E32-F32 | H32: ='Parámetros'!$B$12 | I32: ='Parámetros'!$B$13 | J32: ='Parámetros'!$B$14 | K32: ='Parámetros'!$B$15 | L32: =SUM(H32:K32) | M32: =G32-L32 | N32: =N31+M32
A33: 31 | B33: Jul 2027 | C33: ='Parámetros'!$B$6*(1+'Parámetros'!$B$8)^2 | D33: =IF(31<='Parámetros'!$B$5,0,'Parámetros'!$B$7) | E33: =C33*D33 | F33: =E33*'Parámetros'!$B$11 | G33: =E33-F33 | H33: ='Parámetros'!$B$12 | I33: ='Parámetros'!$B$13 | J33: ='Parámetros'!$B$14 | K33: ='Parámetros'!$B$15 | L33: =SUM(H33:K33) | M33: =G33-L33 | N33: =N32+M33
A34: 32 | B34: Aug 2027 | C34: ='Parámetros'!$B$6*(1+'Parámetros'!$B$8)^2 | D34: =IF(32<='Parámetros'!$B$5,0,'Parámetros'!$B$7) | E34: =C34*D34 | F34: =E34*'Parámetros'!$B$11 | G34: =E34-F34 | H34: ='Parámetros'!$B$12 | I34: ='Parámetros'!$B$13 | J34: ='Parámetros'!$B$14 | K34: ='Parámetros'!$B$15 | L34: =SUM(H34:K34) | M34: =G34-L34 | N34: =N33+M34
A35: 33 | B35: Sep 2027 | C35: ='Parámetros'!$B$6*(1+'Parámetros'!$B$8)^2 | D35: =IF(33<='Parámetros'!$B$5,0,'Parámetros'!$B$7) | E35: =C35*D35 | F35: =E35*'Parámetros'!$B$11 | G35: =E35-F35 | H35: ='Parámetros'!$B$12 | I35: ='Parámetros'!$B$13 | J35: ='Parámetros'!$B$14 | K35: ='Parámetros'!$B$15 | L35: =SUM(H35:K35) | M35: =G35-L35 | N35: =N34+M35
A36: 34 | B36: Oct 2027 | C36: ='Parámetros'!$B$6*(1+'Parámetros'!$B$8)^2 | D36: =IF(34<='Parámetros'!$B$5,0,'Parámetros'!$B$7) | E36: =C36*D36 | F36: =E36*'Parámetros'!$B$11 | G36: =E36-F36 | H36: ='Parámetros'!$B$12 | I36: ='Parámetros'!$B$13 | J36: ='Parámetros'!$B$14 | K36: ='Parámetros'!$B$15 | L36: =SUM(H36:K36) | M36: =G36-L36 | N36: =N35+M36
A37: 35 | B37: Nov 2027 | C37: ='Parámetros'!$B$6*(1+'Parámetros'!$B$8)^2 | D37: =IF(35<='Parámetros'!$B$5,0,'Parámetros'!$B$7) | E37: =C37*D37 | F37: =E37*'Parámetros'!$B$11 | G37: =E37-F37 | H37: ='Parámetros'!$B$12 | I37: ='Parámetros'!$B$13 | J37: ='Parámetros'!$B$14 | K37: ='Parámetros'!$B$15 | L37: =SUM(H37:K37) | M37: =G37-L37 | N37: =N36+M37
A38: 36 | B38: Dec 2027 | C38: ='Parámetros'!$B$6*(1+'Parámetros'!$B$8)^2 | D38: =IF(36<='Parámetros'!$B$5,0,'Parámetros'!$B$7) | E38: =C38*D38 | F38: =E38*'Parámetros'!$B$11 | G38: =E38-F38 | H38: ='Parámetros'!$B$12 | I38: ='Parámetros'!$B$13 | J38: ='Parámetros'!$B$14 | K38: ='Parámetros'!$B$15 | L38: =SUM(H38:K38) | M38: =G38-L38 | N38: =N37+M38
A39: TOTALES | G39: =SUM(G3:G38) | H39: =SUM(H3:H38) | I39: =SUM(I3:I38) | J39: =SUM(J3:J38) | K39: =SUM(K3:K38) | L39: =SUM(L3:L38) | M39: =SUM(M3:M38) | N39: =N38

Sheet Resumen
A1: RESUMEN EJECUTIVO – FLUJO DE CAJA AIRBNB
A3: INVERSIÓN
A4: Inversión inicial (amoblado) | B4: ='Parámetros'!$B$18
A5: Horizonte de análisis | B5: ='Parámetros'!$B$4&" meses"
A6: Meses de gracia | B6: ='Parámetros'!$B$5
A8: INGRESOS ESPERADOS
A9: ADR promedio inicial (CLP/noche) | B9: ='Parámetros'!$B$6
A10: Noches promedio / mes | B10: ='Parámetros'!$B$7
A11: Ingreso bruto mensual promedio | B11: ='Parámetros'!$B$6*'Parámetros'!$B$7
A12: Comisión administración/Airbnb | B12: ='Parámetros'!$B$11
A13: Ingreso neto mensual promedio | B13: ='Parámetros'!$B$6*'Parámetros'!$B$7*(1-'Parámetros'!$B$11)
A15: EGRESOS FIJOS MENSUALES
A16: Gastos comunes | B16: ='Parámetros'!$B$12
A17: Servicios | B17: ='Parámetros'!$B$13
A18: Fondo mantención | B18: ='Parámetros'!$B$14
A19: Dividendo / arriendo | B19: ='Parámetros'!$B$15
A20: Total egresos fijos | B20: ='Parámetros'!$B$12+'Parámetros'!$B$13+'Parámetros'!$B$14+'Parámetros'!$B$15
A22: INDICADORES FINANCIEROS
A23: Tasa de descuento anual | B23: ='Parámetros'!$B$19
A24: Tasa de descuento mensual | B24: =(1+'Parámetros'!$B$19)^(1/12)-1
A25: Flujo neto total (36 meses) | B25: ='Flujo de Caja Mensual'!M39
A26: Flujo acumulado final | B26: ='Flujo de Caja Mensual'!N38
A27: VAN (Valor Actual Neto) | B27: =NPV((1+'Parámetros'!$B$19)^(1/12)-1,'Flujo de Caja Mensual'!M3:'Flujo de Caja Mensual'!M38)-'Parámetros'!$B$18
A28: TIR mensual | B28: =IFERROR(IRR(IF({1},{-'Parámetros'!$B$18,'Flujo de Caja Mensual'!M3:'Flujo de Caja Mensual'!M38})),"N/D")
A29: Payback (mes aprox.) | B29: =IFERROR(MATCH(0,IF('Flujo de Caja Mensual'!N3:'Flujo de Caja Mensual'!N38>0,1,0),0)+'Parámetros'!$B$5,"No recuperado")
A32: Nota: VAN positivo indica que el proyecto genera valor por encima de la tasa de descuento elegida (12% anual). TIR se calcula con flujos mensuales incluyendo la inversión inicial en t=0.
